<?xml version='1.0' encoding='utf-8'?>

<items>
    <buffs classid="PHOENIX_KNIGHT" buffs="1035,4;1036,2;1040,3,1045,6;1068,3;1086,2;1243,6;1259,4;1304,3,1352,1;1353,1;1389,3;1363,1;271,1;274,1;275,1;264,1;267,1;268,1;304,1;1204,2"/>
    <buffs classid="HELL_KNIGHT" buffs="1035,4;1036,2;1040,3,1045,6;1068,3;1086,2;1243,6;1259,4;1304,3,1352,1;1353,1;1389,3;1363,1;271,1;274,1;275,1;264,1;267,1;268,1;304,1;1204,2"/>
    <buffs classid="DUELIST" buffs="1035,4;1036,2;1040,3,1045,6;1068,3;1086,2;1243,6;1259,4;1304,3,1352,1;1353,1;1389,3;1363,1;271,1;274,1;275,1;264,1;267,1;268,1;304,1;1204,2"/>
    <buffs classid="DREADNOUGHT" buffs="1035,4;1036,2;1040,3,1045,6;1068,3;1086,2;1243,6;1259,4;1304,3,1352,1;1353,1;1389,3;1363,1;271,1;274,1;275,1;264,1;267,1;268,1;304,1;1204,2"/>
    <buffs classid="ADVENTURER" buffs="1204,2;1040,3;1036,2;1045,6;1077,3;1068,3;1086,2;1242,3;1363,1;1389,3;271,1;274,1;275,1;264,1;267,1;268,1;269,1;304,1;364,1"/>
    <buffs classid="SAGGITARIUS" buffs="1204,2;1040,3;1036,2;1045,6;1048,6;1062,2;1068,3;1077,3;1086,2;1240,3;1242,3;1388,3;1363,1;271,1;274,1;275,1;264,1;267,1;268,1;269,1;304,1;364,1"/>
    <buffs classid="EVAS_TEMPLAR" buffs="1035,4;1036,2;1040,3,1045,6;1068,3;1086,2;1243,6;1259,4;1304,3,1352,1;1353,1;1389,3;1363,1;271,1;274,1;275,1;264,1;267,1;268,1;304,1;1204,2"/>
    <buffs classid="SWORD_MUSE" buffs="1035,4;1036,2;1040,3,1045,6;1068,3;1086,2;1243,6;1259,4;1304,3,1352,1;1353,1;1389,3;1363,1;271,1;274,1;275,1;264,1;267,1;268,1;304,1;1204,2"/>
    <buffs classid="WIND_RIDER" buffs="1204,2;1040,3;1036,2;1045,6;1077,3;1068,3;1086,2;1242,3;1363,1;1389,3;271,1;274,1;275,1;264,1;267,1;268,1;269,1;304,1;364,1"/>
    <buffs classid="MOONLIGHT_SENTINEL" buffs="1204,2;1040,3;1036,2;1045,6;1048,6;1062,2;1068,3;1077,3;1086,2;1240,3;1242,3;1388,3;1363,1;271,1;274,1;275,1;264,1;267,1;268,1;269,1;304,1;364,1"/>
    <buffs classid="SHILLIEN_TEMPLAR" buffs="1035,4;1036,2;1040,3,1045,6;1068,3;1086,2;1243,6;1259,4;1304,3,1352,1;1353,1;1389,3;1363,1;271,1;274,1;275,1;264,1;267,1;268,1;304,1;1204,2"/>
    <buffs classid="SPECTRAL_DANCER" buffs="1204,2;1040,3;1036,2;1045,6;1048,6;1062,2;1068,3;1077,3;1086,2;1240,3;1242,3;1268,4;1388,3;1363,1;271,1;274,1;275,1;264,1;267,1;268,1;269,1;304,1"/>
    <buffs classid="GHOST_HUNTER" buffs="1204,2;1040,3;1036,2;1045,6;1077,3;1068,3;1086,2;1242,3;1363,1;1389,3;271,1;274,1;275,1;264,1;267,1;268,1;269,1;304,1;364,1"/>
    <buffs classid="GHOST_SENTINEL" buffs="1204,2;1040,3;1036,2;1045,6;1048,6;1062,2;1068,3;1077,3;1086,2;1240,3;1242,3;1388,3;1363,1;271,1;274,1;275,1;264,1;267,1;268,1;269,1;304,1;364,1"/>
    <buffs classid="TITAN" buffs="1204,2;1040,3;1036,2;1045,6;1048,6;1062,2;1068,3;1077,3;1086,2;1240,3;1242,3;1268,4;1388,3;1363,1;271,1;274,1;275,1;264,1;267,1;268,1;269,1;304,1"/>
    <buffs classid="GRAND_KHAVATARI" buffs="1204,2;1040,3;1036,2;1045,6;1048,6;1062,2;1068,3;1077,3;1086,2;1240,3;1242,3;1268,4;1388,3;1363,1;271,1;274,1;275,1;264,1;267,1;268,1;269,1;304,1"/>
    <buffs classid="FORTUNE_SEEKER" buffs="1204,2;1040,3;1036,2;1045,6;1048,6;1062,2;1068,3;1077,3;1086,2;1240,3;1242,3;1268,4;1388,3;1363,1;271,1;274,1;275,1;264,1;267,1;268,1;269,1;304,1"/>
    <buffs classid="MAESTRO" buffs="1204,2;1040,3;1036,2;1045,6;1048,6;1062,2;1068,3;1077,3;1086,2;1240,3;1242,3;1268,4;1388,3;1363,1;271,1;274,1;275,1;264,1;267,1;268,1;269,1;304,1"/>
    <buffs classid="ARCHMAGE" buffs="1204,2;1035,4;1036,2;1040,3;1045,6;1059,3;1062,2;1078,6;1085,3;1303,2;1389,3;1413,1;273,1;276,1;365,1;264,1;267,1;268,1;304,1;349,1;1048,6"/>
    <buffs classid="SOULTAKER" buffs="1204,2;1035,4;1036,2;1040,3;1045,6;1059,3;1062,2;1078,6;1085,3;1303,2;1389,3;1413,1;273,1;276,1;365,1;264,1;267,1;268,1;304,1;349,1;1048,6"/>
    <buffs classid="ARCANA_LORD" buffs="1204,2;1035,4;1036,2;1040,3;1045,6;1059,3;1062,2;1078,6;1085,3;1303,2;1389,3;1413,1;273,1;276,1;365,1;264,1;267,1;268,1;304,1;349,1;1048,6"/>
    <buffs classid="CARDINAL" buffs="1204,2;1035,4;1036,2;1040,3;1045,6;1059,3;1062,2;1078,6;1085,3;1303,2;1389,3;1413,1;273,1;276,1;365,1;264,1;267,1;268,1;304,1;349,1;1048,6"/>
    <buffs classid="HIEROPHANT" buffs="1204,2;1035,4;1036,2;1040,3;1045,6;1059,3;1062,2;1078,6;1085,3;1303,2;1389,3;1413,1;273,1;276,1;365,1;264,1;267,1;268,1;304,1;349,1;1048,6"/>
    <buffs classid="MYSTIC_MUSE" buffs="1204,2;1035,4;1036,2;1040,3;1045,6;1059,3;1062,2;1078,6;1085,3;1303,2;1389,3;1413,1;273,1;276,1;365,1;264,1;267,1;268,1;304,1;349,1;1048,6"/>
    <buffs classid="ELEMENTAL_MASTER" buffs="1204,2;1035,4;1036,2;1040,3;1045,6;1059,3;1062,2;1078,6;1085,3;1303,2;1389,3;1413,1;273,1;276,1;365,1;264,1;267,1;268,1;304,1;349,1;1048,6"/>
    <buffs classid="EVAS_SAINT" buffs="1204,2;1035,4;1036,2;1040,3;1045,6;1059,3;1062,2;1078,6;1085,3;1303,2;1389,3;1413,1;273,1;276,1;365,1;264,1;267,1;268,1;304,1;349,1;1048,6"/>
    <buffs classid="STORM_SCREAMER" buffs="1204,2;1035,4;1036,2;1040,3;1045,6;1059,3;1062,2;1078,6;1085,3;1303,2;1389,3;1413,1;273,1;276,1;365,1;264,1;267,1;268,1;304,1;349,1;1048,6"/>
    <buffs classid="SPECTRAL_MASTER" buffs="1204,2;1035,4;1036,2;1040,3;1045,6;1059,3;1062,2;1078,6;1085,3;1303,2;1389,3;1413,1;273,1;276,1;365,1;264,1;267,1;268,1;304,1;349,1;1048,6"/>
    <buffs classid="SHILLIEN_SAINT" buffs="1204,2;1035,4;1036,2;1040,3;1045,6;1059,3;1062,2;1078,6;1085,3;1303,2;1389,3;1413,1;273,1;276,1;365,1;264,1;267,1;268,1;304,1;349,1;1048,6"/>
    <buffs classid="DOMINATOR" buffs="1204,2;1035,4;1036,2;1040,3;1045,6;1059,3;1062,2;1078,6;1085,3;1303,2;1389,3;1413,1;273,1;276,1;365,1;264,1;267,1;268,1;304,1;349,1;1048,6"/>
    <buffs classid="DOOMCRYER" buffs="1204,2;1040,3;1036,2;1045,6;1048,6;1062,2;1068,3;1077,3;1086,2;1240,3;1242,3;1268,4;1388,3;1363,1;271,1;274,1;275,1;264,1;267,1;268,1;269,1;304,1"/>    
</items>